Workbook

Sheet 每日個股健檢
A1: 每日個股健檢
A2: 使用方式：在淡黃色欄位輸入「交易所:股票代號」（例：TPE:2330、NASDAQ:AAPL）。行情可能延遲最多 20 分鐘，部分市場或欄位可能無資料。
A3: 基本設定
A4: 股票代號 | B4: NASDAQ:SKHY | C4: 中文名稱 | D4: =IFERROR(__xludf.DUMMYFUNCTION("IFERROR(GOOGLETRANSLATE(GOOGLEFINANCE($B$4,""name""),""auto"",""zh-TW""),"""")"),"SK海力士股份有限公司 - ADR") -> SK海力士股份有限公司 - ADR | E4: 英文名稱 | F4: =IFERROR(__xludf.DUMMYFUNCTION("IFERROR(GOOGLEFINANCE($B$4,""name""),"""")"),"SK Hynix Inc - ADR") -> SK Hynix Inc - ADR | G4: 投資週期 | H4: 波段（1–6 月）
A5: 持有狀態 | B5: 持有中 | C5: 持有成本（每股） | D5: 160 | E5: 未實現損益（每股） | F5: =IF(OR(D5="",B9=""),"",B9-D5) -> -16.27 | G5: 未實現損益率 | H5: =IF(OR(D5="",B9=""),"",B9/D5-1) -> -0.1016875
A7: 今日行情
A8: 現價 | C8: 今日漲跌幅 | E8: 開盤價 | G8: 最高價
B9: =IFERROR(__xludf.DUMMYFUNCTION("IFERROR(GOOGLEFINANCE($B$4,""price""),"""")"),143.73) -> 143.73 | D9: =IFERROR(__xludf.DUMMYFUNCTION("IFERROR(GOOGLEFINANCE($B$4,""changepct"")/100,"""")"),-0.0354) -> -0.0354 | F9: =IFERROR(__xludf.DUMMYFUNCTION("IFERROR(GOOGLEFINANCE($B$4,""priceopen""),"""")"),159.88) -> 159.88 | H9: =IFERROR(__xludf.DUMMYFUNCTION("IFERROR(GOOGLEFINANCE($B$4,""high""),"""")"),162.65) -> 162.65
A10: 最低價 | C10: 成交量 | E10: 量比 | G10: 52 週價格位置
B11: =IFERROR(__xludf.DUMMYFUNCTION("IFERROR(GOOGLEFINANCE($B$4,""low""),"""")"),143.51) -> 143.51 | D11: =IFERROR(__xludf.DUMMYFUNCTION("IFERROR(GOOGLEFINANCE($B$4,""volume""),"""")"),834811.0) -> 834811 | F11: =IFERROR(__xludf.DUMMYFUNCTION("IFERROR(D11/GOOGLEFINANCE($B$4,""volumeavg""),"""")"),0.03462262191902436) -> 0.034622622 | H11: =IFERROR(__xludf.DUMMYFUNCTION("IFERROR((B9-GOOGLEFINANCE($B$4,""low52""))/(GOOGLEFINANCE($B$4,""high52"")-GOOGLEFINANCE($B$4,""low52"")),"""")"),0.27178750897343856) -> 0.27178751
A13: 趨勢風險
A14: 5 日報酬 | C14: 20 日報酬 | E14: 60 日報酬 | G14: MA5
B15: {=IF(COUNT('歷史資料'!$E$4:$E$603)<6,"",INDEX('歷史資料'!$E$4:$E$603,COUNT('歷史資料'!$E$4:$E$603))/INDEX('歷史資料'!$E$4:$E$603,COUNT('歷史資料'!$E$4:$E$603)-5)-1)} -> -0.070130038 | D15: {=IF(COUNT('歷史資料'!$E$4:$E$603)<21,"",INDEX('歷史資料'!$E$4:$E$603,COUNT('歷史資料'!$E$4:$E$603))/INDEX('歷史資料'!$E$4:$E$603,COUNT('歷史資料'!$E$4:$E$603)-20)-1)} | F15: {=IF(COUNT('歷史資料'!$E$4:$E$603)<61,"",INDEX('歷史資料'!$E$4:$E$603,COUNT('歷史資料'!$E$4:$E$603))/INDEX('歷史資料'!$E$4:$E$603,COUNT('歷史資料'!$E$4:$E$603)-60)-1)} | H15: {=IFERROR(INDEX('歷史資料'!$K$4:$K$603,COUNT('歷史資料'!$E$4:$E$603)),"")} -> 138.542
A16: MA20 | C16: MA60 | E16: RSI（14） | G16: 波動度（20 日年化）
B17: {=IFERROR(INDEX('歷史資料'!$L$4:$L$603,COUNT('歷史資料'!$E$4:$E$603)),"")} | D17: {=IFERROR(INDEX('歷史資料'!$M$4:$M$603,COUNT('歷史資料'!$E$4:$E$603)),"")} | F17: {=IFERROR(INDEX('歷史資料'!$N$4:$N$603,COUNT('歷史資料'!$E$4:$E$603)),"")} -> 47.727273 | H17: {=IFERROR(INDEX('歷史資料'!$O$4:$O$603,COUNT('歷史資料'!$E$4:$E$603)),"")}
A18: 趨勢狀態 | C18: 風險等級 | E18: 52 週低點 | G18: 52 週高點
B19: =IF(OR(B9="",H15="",B17="",D17=""),"",IFS(AND(B9>H15,H15>B17,B17>D17),"多頭排列",AND(B9<H15,H15<B17,B17<D17),"空頭排列",B9>B17,"偏多震盪",B9<B17,"偏空震盪",TRUE,"盤整")) | D19: =IF(OR(H17="",F17=""),"",IFS(OR(H17>='歷史資料'!$R$4,F17>='歷史資料'!$R$6,F17<='歷史資料'!$R$8),"高",OR(H17>='歷史資料'!$R$3,F17>='歷史資料'!$R$5,F17<='歷史資料'!$R$7),"中",TRUE,"低")) | F19: =IFERROR(__xludf.DUMMYFUNCTION("IFERROR(GOOGLEFINANCE($B$4,""low52""),"""")"),124.8) -> 124.8 | H19: =IFERROR(__xludf.DUMMYFUNCTION("IFERROR(GOOGLEFINANCE($B$4,""high52""),"""")"),194.45) -> 194.45
A21: 基本面
A22: 市值 | C22: 本益比 | E22: EPS | G22: Beta
B23: =IFERROR(__xludf.DUMMYFUNCTION("IFERROR(GOOGLEFINANCE($B$4,""marketcap""),"""")"),1.1446815908E15) -> 1.14468e+15 | D23: =IFERROR(__xludf.DUMMYFUNCTION("IFERROR(GOOGLEFINANCE($B$4,""pe""),"""")"),19.57) -> 19.57 | F23: =IFERROR(__xludf.DUMMYFUNCTION("IFERROR(GOOGLEFINANCE($B$4,""eps""),"""")"),7.34) -> 7.34 | H23: =IFERROR(__xludf.DUMMYFUNCTION("IFERROR(GOOGLEFINANCE($B$4,""beta""),"""")"),"")
A24: 流通股數（手動） | C24: 已發行股數 | E24: 幣別 | G24: 最後交易時間
D25: =IFERROR(__xludf.DUMMYFUNCTION("IFERROR(GOOGLEFINANCE($B$4,""shares""),"""")"),7.30492E9) -> 7304920000 | F25: =IFERROR(__xludf.DUMMYFUNCTION("IFERROR(GOOGLEFINANCE($B$4,""currency""),"""")"),"USD") -> USD | H25: =IFERROR(__xludf.DUMMYFUNCTION("IFERROR(GOOGLEFINANCE($B$4,""tradetime""),"""")"),46234.66666666667) -> 46234.667
A27: 分析摘要
A28: 趨勢 | B28: =IF(B19="","等待足夠歷史資料","趨勢："&B19&"；5／20／60 日報酬為 "&TEXT(B15,"0.0%")&"／"&TEXT(D15,"0.0%")&"／"&TEXT(F15,"0.0%")&"。") -> 等待足夠歷史資料
A29: 量能 | B29: =IF(F11="","等待量能資料","今日成交量 "&TEXT(D11,"#,##0")&" 股，量比 "&TEXT(F11,"0.00x")&IF(F11>=1.5,"，量能明顯放大。",IF(F11<=0.7,"，量能偏弱。","，量能正常。"))) -> 今日成交量 834,811 股，量比 0.03x，量能偏弱。
A30: 估值 | B30: =IF(B23="","估值資料不可用或尚未更新。","市值 "&TEXT(B23,"#,##0")&" "&F25&"；本益比 "&IF(D23="","N/A",TEXT(D23,"0.0x"))&"；EPS "&IF(F23="","N/A",TEXT(F23,"0.00"))&"。") -> 市值 1,144,681,590,800,000 USD；本益比 19.6x；EPS 7.34。
A31: 風險 | B31: =IF(D19="","等待風險資料","風險等級："&D19&"；RSI(14) "&TEXT(F17,"0.0")&"；20 日年化波動度 "&TEXT(H17,"0.0%")&"；52 週位置 "&TEXT(H11,"0.0%")&"。") -> 等待風險資料
A32: 綜合摘要 | B32: =IF(OR(B19="",D19=""),"等待足夠資料","綜合判讀："&IF(AND(OR(B19="多頭排列",B19="偏多震盪"),D19<>"高"),"趨勢偏正向，仍應依個人週期與風險承受度追蹤。",IF(AND(B19="空頭排列",D19="高"),"趨勢與風險均偏不利，宜提高警覺。","訊號分歧，宜等待價格、量能與基本面出現一致性。"))) -> 等待足夠資料
A33: 儲存快照（勾選右側按鈕，即以純值新增一筆） | H33: FALSE
A34: 個人追蹤
A35: 觀察理由 | B35: 預設分析定義：請說明目前最值得追蹤的趨勢、量能、估值或價格位置。資料不足請註明，勿虛構。
A36: 催化因素 | B36: 預設分析定義：請列出可能改變股價或基本面的具體事件，不要只寫「市場轉好」等空泛內容。資料不足請註明，勿虛構。
A37: 主要風險 | B37: 預設分析定義：請指出目前數據已反映的風險，以及尚待確認的外部風險。資料不足請註明，勿虛構。
A38: 下次檢查條件 | B38: 預設分析定義：請使用可以驗證的條件，例如突破或跌破 MA20／MA60、量比超過特定門檻、RSI 進入特定區間、接近 52 週高低點，或公司公布財報與法說。資料不足請註明，勿虛構。
A39: 個人結論 | B39: 預設分析定義：請根據投資週期、持有狀態與持有成本，給出「繼續觀察、等待確認、續抱追蹤、提高警戒」等明確但非絕對化的結論，並簡述原因。資料不足請註明，勿虛構。
A42: 資料來源與限制
A43: GOOGLEFINANCE 官方說明：https://support.google.com/docs/answer/3093281?hl=zh-Hant
A44: 限制：報價可能延遲最多 20 分鐘；部分市場與屬性不支援。中英文名稱由 GOOGLEFINANCE("name") 與 GOOGLETRANSLATE 自動處理；真正的流通股數仍需手動輸入。「已發行股數」來自 GOOGLEFINANCE("shares")，兩者概念不同。

Sheet 歷史資料
A1: 歷史資料（均線、RSI、報酬率與波動度計算） | Q1: 風險判定設定
A2: A:F 由 GOOGLEFINANCE 取得近 500 日每日 OHLCV；G:O 為公式計算。切換主頁股票代號後會自動更新。資料不足時相關指標保持空白。 | Q2: 參數 | R2: 門檻
A3: =IFERROR(__xludf.DUMMYFUNCTION("IF('每日個股健檢'!$B$4="""","""",GOOGLEFINANCE('每日個股健檢'!$B$4,""all"",TODAY()-500,TODAY(),""DAILY""))"),"Date") -> Date | B3: =IFERROR(__xludf.DUMMYFUNCTION("""COMPUTED_VALUE"""),"Open") -> Open | C3: =IFERROR(__xludf.DUMMYFUNCTION("""COMPUTED_VALUE"""),"High") -> High | D3: =IFERROR(__xludf.DUMMYFUNCTION("""COMPUTED_VALUE"""),"Low") -> Low | E3: =IFERROR(__xludf.DUMMYFUNCTION("""COMPUTED_VALUE"""),"Close") -> Close | F3: =IFERROR(__xludf.DUMMYFUNCTION("""COMPUTED_VALUE"""),"Volume") -> Volume | G3: 日報酬 | H3: 漲跌額 | I3: 上漲幅 | J3: 下跌幅 | K3: MA5 | L3: MA20 | M3: MA60 | N3: RSI（14） | O3: 波動度（20 日年化） | Q3: 中風險年化波動度 | R3: 0.25
A4: =IFERROR(__xludf.DUMMYFUNCTION("""COMPUTED_VALUE"""),46213.66666666667) -> 46213.667 | B4: =IFERROR(__xludf.DUMMYFUNCTION("""COMPUTED_VALUE"""),170.0) -> 170 | C4: =IFERROR(__xludf.DUMMYFUNCTION("""COMPUTED_VALUE"""),177.0) -> 177 | D4: =IFERROR(__xludf.DUMMYFUNCTION("""COMPUTED_VALUE"""),166.19) -> 166.19 | E4: =IFERROR(__xludf.DUMMYFUNCTION("""COMPUTED_VALUE"""),168.01) -> 168.01 | F4: =IFERROR(__xludf.DUMMYFUNCTION("""COMPUTED_VALUE"""),1.07674662E8) -> 107674662 | G4: =IFERROR(IF(E4="","",E4/E3-1),"") | H4: =IFERROR(IF(E4="","",E4-E3),"") | I4: =IF(H4="","",MAX(H4,0)) | J4: =IF(H4="","",MAX(-H4,0)) | K4: =IF(E4="","",IF(COUNT($E$4:E4)<5,"",AVERAGE(INDEX($E$4:E4,ROWS($E$4:E4)-4):E4))) | L4: =IF(E4="","",IF(COUNT($E$4:E4)<20,"",AVERAGE(INDEX($E$4:E4,ROWS($E$4:E4)-19):E4))) | M4: =IF(E4="","",IF(COUNT($E$4:E4)<60,"",AVERAGE(INDEX($E$4:E4,ROWS($E$4:E4)-59):E4))) | N4: =IF(E4="","",IF(COUNT($E$4:E4)<15,"",IF(SUM(INDEX($J$4:J4,ROWS($J$4:J4)-13):J4)=0,100,100-100/(1+SUM(INDEX($I$4:I4,ROWS($I$4:I4)-13):I4)/SUM(INDEX($J$4:J4,ROWS($J$4:J4)-13):J4))))) | O4: =IF(G4="","",IF(COUNT($G$4:G4)<20,"",_xlfn.STDEV.S(INDEX($G$4:G4,ROWS($G$4:G4)-19):G4)*SQRT($R$9))) | Q4: 高風險年化波動度 | R4: 0.4
A5: =IFERROR(__xludf.DUMMYFUNCTION("""COMPUTED_VALUE"""),46216.66666666667) -> 46216.667 | B5: =IFERROR(__xludf.DUMMYFUNCTION("""COMPUTED_VALUE"""),152.62) -> 152.62 | C5: =IFERROR(__xludf.DUMMYFUNCTION("""COMPUTED_VALUE"""),162.28) -> 162.28 | D5: =IFERROR(__xludf.DUMMYFUNCTION("""COMPUTED_VALUE"""),151.3) -> 151.3 | E5: =IFERROR(__xludf.DUMMYFUNCTION("""COMPUTED_VALUE"""),152.35) -> 152.35 | F5: =IFERROR(__xludf.DUMMYFUNCTION("""COMPUTED_VALUE"""),5.7284315E7) -> 57284315 | G5: =IFERROR(IF(E5="","",E5/E4-1),"") -> -0.093208738 | H5: =IFERROR(IF(E5="","",E5-E4),"") -> -15.66 | I5: =IF(H5="","",MAX(H5,0)) -> 0 | J5: =IF(H5="","",MAX(-H5,0)) -> 15.66 | K5: =IF(E5="","",IF(COUNT($E$4:E5)<5,"",AVERAGE(INDEX($E$4:E5,ROWS($E$4:E5)-4):E5))) | L5: =IF(E5="","",IF(COUNT($E$4:E5)<20,"",AVERAGE(INDEX($E$4:E5,ROWS($E$4:E5)-19):E5))) | M5: =IF(E5="","",IF(COUNT($E$4:E5)<60,"",AVERAGE(INDEX($E$4:E5,ROWS($E$4:E5)-59):E5))) | N5: =IF(E5="","",IF(COUNT($E$4:E5)<15,"",IF(SUM(INDEX($J$4:J5,ROWS($J$4:J5)-13):J5)=0,100,100-100/(1+SUM(INDEX($I$4:I5,ROWS($I$4:I5)-13):I5)/SUM(INDEX($J$4:J5,ROWS($J$4:J5)-13):J5))))) | O5: =IF(G5="","",IF(COUNT($G$4:G5)<20,"",_xlfn.STDEV.S(INDEX($G$4:G5,ROWS($G$4:G5)-19):G5)*SQRT($R$9))) | Q5: RSI 超買 | R5: 70
A6: =IFERROR(__xludf.DUMMYFUNCTION("""COMPUTED_VALUE"""),46217.66666666667) -> 46217.667 | B6: =IFERROR(__xludf.DUMMYFUNCTION("""COMPUTED_VALUE"""),168.11) -> 168.11 | C6: =IFERROR(__xludf.DUMMYFUNCTION("""COMPUTED_VALUE"""),194.8) -> 194.8 | D6: =IFERROR(__xludf.DUMMYFUNCTION("""COMPUTED_VALUE"""),165.5) -> 165.5 | E6: =IFERROR(__xludf.DUMMYFUNCTION("""COMPUTED_VALUE"""),193.92) -> 193.92 | F6: =IFERROR(__xludf.DUMMYFUNCTION("""COMPUTED_VALUE"""),7.2647674E7) -> 72647674 | G6: =IFERROR(IF(E6="","",E6/E5-1),"") -> 0.27285855 | H6: =IFERROR(IF(E6="","",E6-E5),"") -> 41.57 | I6: =IF(H6="","",MAX(H6,0)) -> 41.57 | J6: =IF(H6="","",MAX(-H6,0)) -> 0 | K6: =IF(E6="","",IF(COUNT($E$4:E6)<5,"",AVERAGE(INDEX($E$4:E6,ROWS($E$4:E6)-4):E6))) | L6: =IF(E6="","",IF(COUNT($E$4:E6)<20,"",AVERAGE(INDEX($E$4:E6,ROWS($E$4:E6)-19):E6))) | M6: =IF(E6="","",IF(COUNT($E$4:E6)<60,"",AVERAGE(INDEX($E$4:E6,ROWS($E$4:E6)-59):E6))) | N6: =IF(E6="","",IF(COUNT($E$4:E6)<15,"",IF(SUM(INDEX($J$4:J6,ROWS($J$4:J6)-13):J6)=0,100,100-100/(1+SUM(INDEX($I$4:I6,ROWS($I$4:I6)-13):I6)/SUM(INDEX($J$4:J6,ROWS($J$4:J6)-13):J6))))) | O6: =IF(G6="","",IF(COUNT($G$4:G6)<20,"",_xlfn.STDEV.S(INDEX($G$4:G6,ROWS($G$4:G6)-19):G6)*SQRT($R$9))) | Q6: RSI 極端超買 | R6: 75
A7: =IFERROR(__xludf.DUMMYFUNCTION("""COMPUTED_VALUE"""),46218.66666666667) -> 46218.667 | B7: =IFERROR(__xludf.DUMMYFUNCTION("""COMPUTED_VALUE"""),181.81) -> 181.81 | C7: =IFERROR(__xludf.DUMMYFUNCTION("""COMPUTED_VALUE"""),187.95) -> 187.95 | D7: =IFERROR(__xludf.DUMMYFUNCTION("""COMPUTED_VALUE"""),166.48) -> 166.48 | E7: =IFERROR(__xludf.DUMMYFUNCTION("""COMPUTED_VALUE"""),176.46) -> 176.46 | F7: =IFERROR(__xludf.DUMMYFUNCTION("""COMPUTED_VALUE"""),7.630766E7) -> 76307660 | G7: =IFERROR(IF(E7="","",E7/E6-1),"") -> -0.090037129 | H7: =IFERROR(IF(E7="","",E7-E6),"") -> -17.46 | I7: =IF(H7="","",MAX(H7,0)) -> 0 | J7: =IF(H7="","",MAX(-H7,0)) -> 17.46 | K7: =IF(E7="","",IF(COUNT($E$4:E7)<5,"",AVERAGE(INDEX($E$4:E7,ROWS($E$4:E7)-4):E7))) | L7: =IF(E7="","",IF(COUNT($E$4:E7)<20,"",AVERAGE(INDEX($E$4:E7,ROWS($E$4:E7)-19):E7))) | M7: =IF(E7="","",IF(COUNT($E$4:E7)<60,"",AVERAGE(INDEX($E$4:E7,ROWS($E$4:E7)-59):E7))) | N7: =IF(E7="","",IF(COUNT($E$4:E7)<15,"",IF(SUM(INDEX($J$4:J7,ROWS($J$4:J7)-13):J7)=0,100,100-100/(1+SUM(INDEX($I$4:I7,ROWS($I$4:I7)-13):I7)/SUM(INDEX($J$4:J7,ROWS($J$4:J7)-13):J7))))) | O7: =IF(G7="","",IF(COUNT($G$4:G7)<20,"",_xlfn.STDEV.S(INDEX($G$4:G7,ROWS($G$4:G7)-19):G7)*SQRT($R$9))) | Q7: RSI 超賣 | R7: 30
A8: =IFERROR(__xludf.DUMMYFUNCTION("""COMPUTED_VALUE"""),46219.66666666667) -> 46219.667 | B8: =IFERROR(__xludf.DUMMYFUNCTION("""COMPUTED_VALUE"""),165.91) -> 165.91 | C8: =IFERROR(__xludf.DUMMYFUNCTION("""COMPUTED_VALUE"""),168.2) -> 168.2 | D8: =IFERROR(__xludf.DUMMYFUNCTION("""COMPUTED_VALUE"""),151.38) -> 151.38 | E8: =IFERROR(__xludf.DUMMYFUNCTION("""COMPUTED_VALUE"""),152.31) -> 152.31 | F8: =IFERROR(__xludf.DUMMYFUNCTION("""COMPUTED_VALUE"""),5.6250532E7) -> 56250532 | G8: =IFERROR(IF(E8="","",E8/E7-1),"") -> -0.13685821 | H8: =IFERROR(IF(E8="","",E8-E7),"") -> -24.15 | I8: =IF(H8="","",MAX(H8,0)) -> 0 | J8: =IF(H8="","",MAX(-H8,0)) -> 24.15 | K8: =IF(E8="","",IF(COUNT($E$4:E8)<5,"",AVERAGE(INDEX($E$4:E8,ROWS($E$4:E8)-4):E8))) -> 168.61 | L8: =IF(E8="","",IF(COUNT($E$4:E8)<20,"",AVERAGE(INDEX($E$4:E8,ROWS($E$4:E8)-19):E8))) | M8: =IF(E8="","",IF(COUNT($E$4:E8)<60,"",AVERAGE(INDEX($E$4:E8,ROWS($E$4:E8)-59):E8))) | N8: =IF(E8="","",IF(COUNT($E$4:E8)<15,"",IF(SUM(INDEX($J$4:J8,ROWS($J$4:J8)-13):J8)=0,100,100-100/(1+SUM(INDEX($I$4:I8,ROWS($I$4:I8)-13):I8)/SUM(INDEX($J$4:J8,ROWS($J$4:J8)-13):J8))))) | O8: =IF(G8="","",IF(COUNT($G$4:G8)<20,"",_xlfn.STDEV.S(INDEX($G$4:G8,ROWS($G$4:G8)-19):G8)*SQRT($R$9))) | Q8: RSI 極端超賣 | R8: 25
A9: =IFERROR(__xludf.DUMMYFUNCTION("""COMPUTED_VALUE"""),46220.66666666667) -> 46220.667 | B9: =IFERROR(__xludf.DUMMYFUNCTION("""COMPUTED_VALUE"""),152.11) -> 152.11 | C9: =IFERROR(__xludf.DUMMYFUNCTION("""COMPUTED_VALUE"""),167.37) -> 167.37 | D9: =IFERROR(__xludf.DUMMYFUNCTION("""COMPUTED_VALUE"""),145.57) -> 145.57 | E9: =IFERROR(__xludf.DUMMYFUNCTION("""COMPUTED_VALUE"""),154.03) -> 154.03 | F9: =IFERROR(__xludf.DUMMYFUNCTION("""COMPUTED_VALUE"""),7.3978315E7) -> 73978315 | G9: =IFERROR(IF(E9="","",E9/E8-1),"") -> 0.011292758 | H9: =IFERROR(IF(E9="","",E9-E8),"") -> 1.72 | I9: =IF(H9="","",MAX(H9,0)) -> 1.72 | J9: =IF(H9="","",MAX(-H9,0)) -> 0 | K9: =IF(E9="","",IF(COUNT($E$4:E9)<5,"",AVERAGE(INDEX($E$4:E9,ROWS($E$4:E9)-4):E9))) -> 165.814 | L9: =IF(E9="","",IF(COUNT($E$4:E9)<20,"",AVERAGE(INDEX($E$4:E9,ROWS($E$4:E9)-19):E9))) | M9: =IF(E9="","",IF(COUNT($E$4:E9)<60,"",AVERAGE(INDEX($E$4:E9,ROWS($E$4:E9)-59):E9))) | N9: =IF(E9="","",IF(COUNT($E$4:E9)<15,"",IF(SUM(INDEX($J$4:J9,ROWS($J$4:J9)-13):J9)=0,100,100-100/(1+SUM(INDEX($I$4:I9,ROWS($I$4:I9)-13):I9)/SUM(INDEX($J$4:J9,ROWS($J$4:J9)-13):J9))))) | O9: =IF(G9="","",IF(COUNT($G$4:G9)<20,"",_xlfn.STDEV.S(INDEX($G$4:G9,ROWS($G$4:G9)-19):G9)*SQRT($R$9))) | Q9: 年交易日數 | R9: 252
A10: =IFERROR(__xludf.DUMMYFUNCTION("""COMPUTED_VALUE"""),46223.66666666667) -> 46223.667 | B10: =IFERROR(__xludf.DUMMYFUNCTION("""COMPUTED_VALUE"""),163.42) -> 163.42 | C10: =IFERROR(__xludf.DUMMYFUNCTION("""COMPUTED_VALUE"""),163.43) -> 163.43 | D10: =IFERROR(__xludf.DUMMYFUNCTION("""COMPUTED_VALUE"""),149.74) -> 149.74 | E10: =IFERROR(__xludf.DUMMYFUNCTION("""COMPUTED_VALUE"""),151.16) -> 151.16 | F10: =IFERROR(__xludf.DUMMYFUNCTION("""COMPUTED_VALUE"""),3.7817455E7) -> 37817455 | G10: =IFERROR(IF(E10="","",E10/E9-1),"") -> -0.018632734 | H10: =IFERROR(IF(E10="","",E10-E9),"") -> -2.87 | I10: =IF(H10="","",MAX(H10,0)) -> 0 | J10: =IF(H10="","",MAX(-H10,0)) -> 2.87 | K10: =IF(E10="","",IF(COUNT($E$4:E10)<5,"",AVERAGE(INDEX($E$4:E10,ROWS($E$4:E10)-4):E10))) -> 165.576 | L10: =IF(E10="","",IF(COUNT($E$4:E10)<20,"",AVERAGE(INDEX($E$4:E10,ROWS($E$4:E10)-19):E10))) | M10: =IF(E10="","",IF(COUNT($E$4:E10)<60,"",AVERAGE(INDEX($E$4:E10,ROWS($E$4:E10)-59):E10))) | N10: =IF(E10="","",IF(COUNT($E$4:E10)<15,"",IF(SUM(INDEX($J$4:J10,ROWS($J$4:J10)-13):J10)=0,100,100-100/(1+SUM(INDEX($I$4:I10,ROWS($I$4:I10)-13):I10)/SUM(INDEX($J$4:J10,ROWS($J$4:J10)-13):J10))))) | O10: =IF(G10="","",IF(COUNT($G$4:G10)<20,"",_xlfn.STDEV.S(INDEX($G$4:G10,ROWS($G$4:G10)-19):G10)*SQRT($R$9)))
A11: =IFERROR(__xludf.DUMMYFUNCTION("""COMPUTED_VALUE"""),46224.66666666667) -> 46224.667 | B11: =IFERROR(__xludf.DUMMYFUNCTION("""COMPUTED_VALUE"""),161.75) -> 161.75 | C11: =IFERROR(__xludf.DUMMYFUNCTION("""COMPUTED_VALUE"""),173.22) -> 173.22 | D11: =IFERROR(__xludf.DUMMYFUNCTION("""COMPUTED_VALUE"""),160.54) -> 160.54 | E11: =IFERROR(__xludf.DUMMYFUNCTION("""COMPUTED_VALUE"""),171.94) -> 171.94 | F11: =IFERROR(__xludf.DUMMYFUNCTION("""COMPUTED_VALUE"""),3.8925609E7) -> 38925609 | G11: =IFERROR(IF(E11="","",E11/E10-1),"") -> 0.13747023 | H11: =IFERROR(IF(E11="","",E11-E10),"") -> 20.78 | I11: =IF(H11="","",MAX(H11,0)) -> 20.78 | J11: =IF(H11="","",MAX(-H11,0)) -> 0 | K11: =IF(E11="","",IF(COUNT($E$4:E11)<5,"",AVERAGE(INDEX($E$4:E11,ROWS($E$4:E11)-4):E11))) -> 161.18 | L11: =IF(E11="","",IF(COUNT($E$4:E11)<20,"",AVERAGE(INDEX($E$4:E11,ROWS($E$4:E11)-19):E11))) | M11: =IF(E11="","",IF(COUNT($E$4:E11)<60,"",AVERAGE(INDEX($E$4:E11,ROWS($E$4:E11)-59):E11))) | N11: =IF(E11="","",IF(COUNT($E$4:E11)<15,"",IF(SUM(INDEX($J$4:J11,ROWS($J$4:J11)-13):J11)=0,100,100-100/(1+SUM(INDEX($I$4:I11,ROWS($I$4:I11)-13):I11)/SUM(INDEX($J$4:J11,ROWS($J$4:J11)-13):J11))))) | O11: =IF(G11="","",IF(COUNT($G$4:G11)<20,"",_xlfn.STDEV.S(INDEX($G$4:G11,ROWS($G$4:G11)-19):G11)*SQRT($R$9)))
A12: =IFERROR(__xludf.DUMMYFUNCTION("""COMPUTED_VALUE"""),46225.66666666667) -> 46225.667 | B12: =IFERROR(__xludf.DUMMYFUNCTION("""COMPUTED_VALUE"""),162.16) -> 162.16 | C12: =IFERROR(__xludf.DUMMYFUNCTION("""COMPUTED_VALUE"""),170.09) -> 170.09 | D12: =IFERROR(__xludf.DUMMYFUNCTION("""COMPUTED_VALUE"""),162.0) -> 162 | E12: =IFERROR(__xludf.DUMMYFUNCTION("""COMPUTED_VALUE"""),165.27) -> 165.27 | F12: =IFERROR(__xludf.DUMMYFUNCTION("""COMPUTED_VALUE"""),2.7122764E7) -> 27122764 | G12: =IFERROR(IF(E12="","",E12/E11-1),"") -> -0.038792602 | H12: =IFERROR(IF(E12="","",E12-E11),"") -> -6.67 | I12: =IF(H12="","",MAX(H12,0)) -> 0 | J12: =IF(H12="","",MAX(-H12,0)) -> 6.67 | K12: =IF(E12="","",IF(COUNT($E$4:E12)<5,"",AVERAGE(INDEX($E$4:E12,ROWS($E$4:E12)-4):E12))) -> 158.942 | L12: =IF(E12="","",IF(COUNT($E$4:E12)<20,"",AVERAGE(INDEX($E$4:E12,ROWS($E$4:E12)-19):E12))) | M12: =IF(E12="","",IF(COUNT($E$4:E12)<60,"",AVERAGE(INDEX($E$4:E12,ROWS($E$4:E12)-59):E12))) | N12: =IF(E12="","",IF(COUNT($E$4:E12)<15,"",IF(SUM(INDEX($J$4:J12,ROWS($J$4:J12)-13):J12)=0,100,100-100/(1+SUM(INDEX($I$4:I12,ROWS($I$4:I12)-13):I12)/SUM(INDEX($J$4:J12,ROWS($J$4:J12)-13):J12))))) | O12: =IF(G12="","",IF(COUNT($G$4:G12)<20,"",_xlfn.STDEV.S(INDEX($G$4:G12,ROWS($G$4:G12)-19):G12)*SQRT($R$9)))
A13: =IFERROR(__xludf.DUMMYFUNCTION("""COMPUTED_VALUE"""),46226.66666666667) -> 46226.667 | B13: =IFERROR(__xludf.DUMMYFUNCTION("""COMPUTED_VALUE"""),170.72) -> 170.72 | C13: =IFERROR(__xludf.DUMMYFUNCTION("""COMPUTED_VALUE"""),177.93) -> 177.93 | D13: =IFERROR(__xludf.DUMMYFUNCTION("""COMPUTED_VALUE"""),167.02) -> 167.02 | E13: =IFERROR(__xludf.DUMMYFUNCTION("""COMPUTED_VALUE"""),169.5) -> 169.5 | F13: =IFERROR(__xludf.DUMMYFUNCTION("""COMPUTED_VALUE"""),3.6234862E7) -> 36234862 | G13: =IFERROR(IF(E13="","",E13/E12-1),"") -> 0.025594482 | H13: =IFERROR(IF(E13="","",E13-E12),"") -> 4.23 | I13: =IF(H13="","",MAX(H13,0)) -> 4.23 | J13: =IF(H13="","",MAX(-H13,0)) -> 0 | K13: =IF(E13="","",IF(COUNT($E$4:E13)<5,"",AVERAGE(INDEX($E$4:E13,ROWS($E$4:E13)-4):E13))) -> 162.38 | L13: =IF(E13="","",IF(COUNT($E$4:E13)<20,"",AVERAGE(INDEX($E$4:E13,ROWS($E$4:E13)-19):E13))) | M13: =IF(E13="","",IF(COUNT($E$4:E13)<60,"",AVERAGE(INDEX($E$4:E13,ROWS($E$4:E13)-59):E13))) | N13: =IF(E13="","",IF(COUNT($E$4:E13)<15,"",IF(SUM(INDEX($J$4:J13,ROWS($J$4:J13)-13):J13)=0,100,100-100/(1+SUM(INDEX($I$4:I13,ROWS($I$4:I13)-13):I13)/SUM(INDEX($J$4:J13,ROWS($J$4:J13)-13):J13))))) | O13: =IF(G13="","",IF(COUNT($G$4:G13)<20,"",_xlfn.STDEV.S(INDEX($G$4:G13,ROWS($G$4:G13)-19):G13)*SQRT($R$9)))
A14: =IFERROR(__xludf.DUMMYFUNCTION("""COMPUTED_VALUE"""),46227.66666666667) -> 46227.667 | B14: =IFERROR(__xludf.DUMMYFUNCTION("""COMPUTED_VALUE"""),163.91) -> 163.91 | C14: =IFERROR(__xludf.DUMMYFUNCTION("""COMPUTED_VALUE"""),164.2) -> 164.2 | D14: =IFERROR(__xludf.DUMMYFUNCTION("""COMPUTED_VALUE"""),153.1) -> 153.1 | E14: =IFERROR(__xludf.DUMMYFUNCTION("""COMPUTED_VALUE"""),154.57) -> 154.57 | F14: =IFERROR(__xludf.DUMMYFUNCTION("""COMPUTED_VALUE"""),2.6255531E7) -> 26255531 | G14: =IFERROR(IF(E14="","",E14/E13-1),"") -> -0.088082596 | H14: =IFERROR(IF(E14="","",E14-E13),"") -> -14.93 | I14: =IF(H14="","",MAX(H14,0)) -> 0 | J14: =IF(H14="","",MAX(-H14,0)) -> 14.93 | K14: =IF(E14="","",IF(COUNT($E$4:E14)<5,"",AVERAGE(INDEX($E$4:E14,ROWS($E$4:E14)-4):E14))) -> 162.488 | L14: =IF(E14="","",IF(COUNT($E$4:E14)<20,"",AVERAGE(INDEX($E$4:E14,ROWS($E$4:E14)-19):E14))) | M14: =IF(E14="","",IF(COUNT($E$4:E14)<60,"",AVERAGE(INDEX($E$4:E14,ROWS($E$4:E14)-59):E14))) | N14: =IF(E14="","",IF(COUNT($E$4:E14)<15,"",IF(SUM(INDEX($J$4:J14,ROWS($J$4:J14)-13):J14)=0,100,100-100/(1+SUM(INDEX($I$4:I14,ROWS($I$4:I14)-13):I14)/SUM(INDEX($J$4:J14,ROWS($J$4:J14)-13):J14))))) | O14: =IF(G14="","",IF(COUNT($G$4:G14)<20,"",_xlfn.STDEV.S(INDEX($G$4:G14,ROWS($G$4:G14)-19):G14)*SQRT($R$9)))
A15: =IFERROR(__xludf.DUMMYFUNCTION("""COMPUTED_VALUE"""),46230.66666666667) -> 46230.667 | B15: =IFERROR(__xludf.DUMMYFUNCTION("""COMPUTED_VALUE"""),159.7) -> 159.7 | C15: =IFERROR(__xludf.DUMMYFUNCTION("""COMPUTED_VALUE"""),159.71) -> 159.71 | D15: =IFERROR(__xludf.DUMMYFUNCTION("""COMPUTED_VALUE"""),139.01) -> 139.01 | E15: =IFERROR(__xludf.DUMMYFUNCTION("""COMPUTED_VALUE"""),143.02) -> 143.02 | F15: =IFERROR(__xludf.DUMMYFUNCTION("""COMPUTED_VALUE"""),5.0747385E7) -> 50747385 | G15: =IFERROR(IF(E15="","",E15/E14-1),"") -> -0.074723426 | H15: =IFERROR(IF(E15="","",E15-E14),"") -> -11.55 | I15: =IF(H15="","",MAX(H15,0)) -> 0 | J15: =IF(H15="","",MAX(-H15,0)) -> 11.55 | K15: =IF(E15="","",IF(COUNT($E$4:E15)<5,"",AVERAGE(INDEX($E$4:E15,ROWS($E$4:E15)-4):E15))) -> 160.86 | L15: =IF(E15="","",IF(COUNT($E$4:E15)<20,"",AVERAGE(INDEX($E$4:E15,ROWS($E$4:E15)-19):E15))) | M15: =IF(E15="","",IF(COUNT($E$4:E15)<60,"",AVERAGE(INDEX($E$4:E15,ROWS($E$4:E15)-59):E15))) | N15: =IF(E15="","",IF(COUNT($E$4:E15)<15,"",IF(SUM(INDEX($J$4:J15,ROWS($J$4:J15)-13):J15)=0,100,100-100/(1+SUM(INDEX($I$4:I15,ROWS($I$4:I15)-13):I15)/SUM(INDEX($J$4:J15,ROWS($J$4:J15)-13):J15))))) | O15: =IF(G15="","",IF(COUNT($G$4:G15)<20,"",_xlfn.STDEV.S(INDEX($G$4:G15,ROWS($G$4:G15)-19):G15)*SQRT($R$9)))
A16: =IFERROR(__xludf.DUMMYFUNCTION("""COMPUTED_VALUE"""),46231.66666666667) -> 46231.667 | B16: =IFERROR(__xludf.DUMMYFUNCTION("""COMPUTED_VALUE"""),135.91) -> 135.91 | C16: =IFERROR(__xludf.DUMMYFUNCTION("""COMPUTED_VALUE"""),136.49) -> 136.49 | D16: =IFERROR(__xludf.DUMMYFUNCTION("""COMPUTED_VALUE"""),128.29) -> 128.29 | E16: =IFERROR(__xludf.DUMMYFUNCTION("""COMPUTED_VALUE"""),130.17) -> 130.17 | F16: =IFERROR(__xludf.DUMMYFUNCTION("""COMPUTED_VALUE"""),5.1088282E7) -> 51088282 | G16: =IFERROR(IF(E16="","",E16/E15-1),"") -> -0.089847574 | H16: =IFERROR(IF(E16="","",E16-E15),"") -> -12.85 | I16: =IF(H16="","",MAX(H16,0)) -> 0 | J16: =IF(H16="","",MAX(-H16,0)) -> 12.85 | K16: =IF(E16="","",IF(COUNT($E$4:E16)<5,"",AVERAGE(INDEX($E$4:E16,ROWS($E$4:E16)-4):E16))) -> 152.506 | L16: =IF(E16="","",IF(COUNT($E$4:E16)<20,"",AVERAGE(INDEX($E$4:E16,ROWS($E$4:E16)-19):E16))) | M16: =IF(E16="","",IF(COUNT($E$4:E16)<60,"",AVERAGE(INDEX($E$4:E16,ROWS($E$4:E16)-59):E16))) | N16: =IF(E16="","",IF(COUNT($E$4:E16)<15,"",IF(SUM(INDEX($J$4:J16,ROWS($J$4:J16)-13):J16)=0,100,100-100/(1+SUM(INDEX($I$4:I16,ROWS($I$4:I16)-13):I16)/SUM(INDEX($J$4:J16,ROWS($J$4:J16)-13):J16))))) | O16: =IF(G16="","",IF(COUNT($G$4:G16)<20,"",_xlfn.STDEV.S(INDEX($G$4:G16,ROWS($G$4:G16)-19):G16)*SQRT($R$9)))
A17: =IFERROR(__xludf.DUMMYFUNCTION("""COMPUTED_VALUE"""),46232.66666666667) -> 46232.667 | B17: =IFERROR(__xludf.DUMMYFUNCTION("""COMPUTED_VALUE"""),129.95) -> 129.95 | C17: =IFERROR(__xludf.DUMMYFUNCTION("""COMPUTED_VALUE"""),137.19) -> 137.19 | D17: =IFERROR(__xludf.DUMMYFUNCTION("""COMPUTED_VALUE"""),124.8) -> 124.8 | E17: =IFERROR(__xludf.DUMMYFUNCTION("""COMPUTED_VALUE"""),126.79) -> 126.79 | F17: =IFERROR(__xludf.DUMMYFUNCTION("""COMPUTED_VALUE"""),6.5810027E7) -> 65810027 | G17: =IFERROR(IF(E17="","",E17/E16-1),"") -> -0.025966044 | H17: =IFERROR(IF(E17="","",E17-E16),"") -> -3.38 | I17: =IF(H17="","",MAX(H17,0)) -> 0 | J17: =IF(H17="","",MAX(-H17,0)) -> 3.38 | K17: =IF(E17="","",IF(COUNT($E$4:E17)<5,"",AVERAGE(INDEX($E$4:E17,ROWS($E$4:E17)-4):E17))) -> 144.81 | L17: =IF(E17="","",IF(COUNT($E$4:E17)<20,"",AVERAGE(INDEX($E$4:E17,ROWS($E$4:E17)-19):E17))) | M17: =IF(E17="","",IF(COUNT($E$4:E17)<60,"",AVERAGE(INDEX($E$4:E17,ROWS($E$4:E17)-59):E17))) | N17: =IF(E17="","",IF(COUNT($E$4:E17)<15,"",IF(SUM(INDEX($J$4:J17,ROWS($J$4:J17)-13):J17)=0,100,100-100/(1+SUM(INDEX($I$4:I17,ROWS($I$4:I17)-13):I17)/SUM(INDEX($J$4:J17,ROWS($J$4:J17)-13):J17))))) | O17: =IF(G17="","",IF(COUNT($G$4:G17)<20,"",_xlfn.STDEV.S(INDEX($G$4:G17,ROWS($G$4:G17)-19):G17)*SQRT($R$9)))
A18: =IFERROR(__xludf.DUMMYFUNCTION("""COMPUTED_VALUE"""),46233.66666666667) -> 46233.667 | B18: =IFERROR(__xludf.DUMMYFUNCTION("""COMPUTED_VALUE"""),136.51) -> 136.51 | C18: =IFERROR(__xludf.DUMMYFUNCTION("""COMPUTED_VALUE"""),150.36) -> 150.36 | D18: =IFERROR(__xludf.DUMMYFUNCTION("""COMPUTED_VALUE"""),134.5) -> 134.5 | E18: =IFERROR(__xludf.DUMMYFUNCTION("""COMPUTED_VALUE"""),149.0) -> 149 | F18: =IFERROR(__xludf.DUMMYFUNCTION("""COMPUTED_VALUE"""),5.288124E7) -> 52881240 | G18: =IFERROR(IF(E18="","",E18/E17-1),"") -> 0.17517154 | H18: =IFERROR(IF(E18="","",E18-E17),"") -> 22.21 | I18: =IF(H18="","",MAX(H18,0)) -> 22.21 | J18: =IF(H18="","",MAX(-H18,0)) -> 0 | K18: =IF(E18="","",IF(COUNT($E$4:E18)<5,"",AVERAGE(INDEX($E$4:E18,ROWS($E$4:E18)-4):E18))) -> 140.71 | L18: =IF(E18="","",IF(COUNT($E$4:E18)<20,"",AVERAGE(INDEX($E$4:E18,ROWS($E$4:E18)-19):E18))) | M18: =IF(E18="","",IF(COUNT($E$4:E18)<60,"",AVERAGE(INDEX($E$4:E18,ROWS($E$4:E18)-59):E18))) | N18: =IF(E18="","",IF(COUNT($E$4:E18)<15,"",IF(SUM(INDEX($J$4:J18,ROWS($J$4:J18)-13):J18)=0,100,100-100/(1+SUM(INDEX($I$4:I18,ROWS($I$4:I18)-13):I18)/SUM(INDEX($J$4:J18,ROWS($J$4:J18)-13):J18))))) -> 45.248213 | O18: =IF(G18="","",IF(COUNT($G$4:G18)<20,"",_xlfn.STDEV.S(INDEX($G$4:G18,ROWS($G$4:G18)-19):G18)*SQRT($R$9)))
A19: =IFERROR(__xludf.DUMMYFUNCTION("""COMPUTED_VALUE"""),46234.66666666667) -> 46234.667 | B19: =IFERROR(__xludf.DUMMYFUNCTION("""COMPUTED_VALUE"""),159.88) -> 159.88 | C19: =IFERROR(__xludf.DUMMYFUNCTION("""COMPUTED_VALUE"""),162.65) -> 162.65 | D19: =IFERROR(__xludf.DUMMYFUNCTION("""COMPUTED_VALUE"""),143.51) -> 143.51 | E19: =IFERROR(__xludf.DUMMYFUNCTION("""COMPUTED_VALUE"""),143.73) -> 143.73 | F19: =IFERROR(__xludf.DUMMYFUNCTION("""COMPUTED_VALUE"""),4.6065094E7) -> 46065094 | G19: =IFERROR(IF(E19="","",E19/E18-1),"") -> -0.035369128 | H19: =IFERROR(IF(E19="","",E19-E18),"") -> -5.27 | I19: =IF(H19="","",MAX(H19,0)) -> 0 | J19: =IF(H19="","",MAX(-H19,0)) -> 5.27 | K19: =IF(E19="","",IF(COUNT($E$4:E19)<5,"",AVERAGE(INDEX($E$4:E19,ROWS($E$4:E19)-4):E19))) -> 138.542 | L19: =IF(E19="","",IF(COUNT($E$4:E19)<20,"",AVERAGE(INDEX($E$4:E19,ROWS($E$4:E19)-19):E19))) | M19: =IF(E19="","",IF(COUNT($E$4:E19)<60,"",AVERAGE(INDEX($E$4:E19,ROWS($E$4:E19)-59):E19))) | N19: =IF(E19="","",IF(COUNT($E$4:E19)<15,"",IF(SUM(INDEX($J$4:J19,ROWS($J$4:J19)-13):J19)=0,100,100-100/(1+SUM(INDEX($I$4:I19,ROWS($I$4:I19)-13):I19)/SUM(INDEX($J$4:J19,ROWS($J$4:J19)-13):J19))))) -> 47.727273 | O19: =IF(G19="","",IF(COUNT($G$4:G19)<20,"",_xlfn.STDEV.S(INDEX($G$4:G19,ROWS($G$4:G19)-19):G19)*SQRT($R$9)))
G20: =IFERROR(IF(E20="","",E20/E19-1),"") | H20: =IFERROR(IF(E20="","",E20-E19),"") | I20: =IF(H20="","",MAX(H20,0)) | J20: =IF(H20="","",MAX(-H20,0)) | K20: =IF(E20="","",IF(COUNT($E$4:E20)<5,"",AVERAGE(INDEX($E$4:E20,ROWS($E$4:E20)-4):E20))) | L20: =IF(E20="","",IF(COUNT($E$4:E20)<20,"",AVERAGE(INDEX($E$4:E20,ROWS($E$4:E20)-19):E20))) | M20: =IF(E20="","",IF(COUNT($E$4:E20)<60,"",AVERAGE(INDEX($E$4:E20,ROWS($E$4:E20)-59):E20))) | N20: =IF(E20="","",IF(COUNT($E$4:E20)<15,"",IF(SUM(INDEX($J$4:J20,ROWS($J$4:J20)-13):J20)=0,100,100-100/(1+SUM(INDEX($I$4:I20,ROWS($I$4:I20)-13):I20)/SUM(INDEX($J$4:J20,ROWS($J$4:J20)-13):J20))))) | O20: =IF(G20="","",IF(COUNT($G$4:G20)<20,"",_xlfn.STDEV.S(INDEX($G$4:G20,ROWS($G$4:G20)-19):G20)*SQRT($R$9)))
G21: =IFERROR(IF(E21="","",E21/E20-1),"") | H21: =IFERROR(IF(E21="","",E21-E20),"") | I21: =IF(H21="","",MAX(H21,0)) | J21: =IF(H21="","",MAX(-H21,0)) | K21: =IF(E21="","",IF(COUNT($E$4:E21)<5,"",AVERAGE(INDEX($E$4:E21,ROWS($E$4:E21)-4):E21))) | L21: =IF(E21="","",IF(COUNT($E$4:E21)<20,"",AVERAGE(INDEX($E$4:E21,ROWS($E$4:E21)-19):E21))) | M21: =IF(E21="","",IF(COUNT($E$4:E21)<60,"",AVERAGE(INDEX($E$4:E21,ROWS($E$4:E21)-59):E21))) | N21: =IF(E21="","",IF(COUNT($E$4:E21)<15,"",IF(SUM(INDEX($J$4:J21,ROWS($J$4:J21)-13):J21)=0,100,100-100/(1+SUM(INDEX($I$4:I21,ROWS($I$4:I21)-13):I21)/SUM(INDEX($J$4:J21,ROWS($J$4:J21)-13):J21))))) | O21: =IF(G21="","",IF(COUNT($G$4:G21)<20,"",_xlfn.STDEV.S(INDEX($G$4:G21,ROWS($G$4:G21)-19):G21)*SQRT($R$9)))
G22: =IFERROR(IF(E22="","",E22/E21-1),"") | H22: =IFERROR(IF(E22="","",E22-E21),"") | I22: =IF(H22="","",MAX(H22,0)) | J22: =IF(H22="","",MAX(-H22,0)) | K22: =IF(E22="","",IF(COUNT($E$4:E22)<5,"",AVERAGE(INDEX($E$4:E22,ROWS($E$4:E22)-4):E22))) | L22: =IF(E22="","",IF(COUNT($E$4:E22)<20,"",AVERAGE(INDEX($E$4:E22,ROWS($E$4:E22)-19):E22))) | M22: =IF(E22="","",IF(COUNT($E$4:E22)<60,"",AVERAGE(INDEX($E$4:E22,ROWS($E$4:E22)-59):E22))) | N22: =IF(E22="","",IF(COUNT($E$4:E22)<15,"",IF(SUM(INDEX($J$4:J22,ROWS($J$4:J22)-13):J22)=0,100,100-100/(1+SUM(INDEX($I$4:I22,ROWS($I$4:I22)-13):I22)/SUM(INDEX($J$4:J22,ROWS($J$4:J22)-13):J22))))) | O22: =IF(G22="","",IF(COUNT($G$4:G22)<20,"",_xlfn.STDEV.S(INDEX($G$4:G22,ROWS($G$4:G22)-19):G22)*SQRT($R$9)))
G23: =IFERROR(IF(E23="","",E23/E22-1),"") | H23: =IFERROR(IF(E23="","",E23-E22),"") | I23: =IF(H23="","",MAX(H23,0)) | J23: =IF(H23="","",MAX(-H23,0)) | K23: =IF(E23="","",IF(COUNT($E$4:E23)<5,"",AVERAGE(INDEX($E$4:E23,ROWS($E$4:E23)-4):E23))) | L23: =IF(E23="","",IF(COUNT($E$4:E23)<20,"",AVERAGE(INDEX($E$4:E23,ROWS($E$4:E23)-19):E23))) | M23: =IF(E23="","",IF(COUNT($E$4:E23)<60,"",AVERAGE(INDEX($E$4:E23,ROWS($E$4:E23)-59):E23))) | N23: =IF(E23="","",IF(COUNT($E$4:E23)<15,"",IF(SUM(INDEX($J$4:J23,ROWS($J$4:J23)-13):J23)=0,100,100-100/(1+SUM(INDEX($I$4:I23,ROWS($I$4:I23)-13):I23)/SUM(INDEX($J$4:J23,ROWS($J$4:J23)-13):J23))))) | O23: =IF(G23="","",IF(COUNT($G$4:G23)<20,"",_xlfn.STDEV.S(INDEX($G$4:G23,ROWS($G$4:G23)-19):G23)*SQRT($R$9)))
G24: =IFERROR(IF(E24="","",E24/E23-1),"") | H24: =IFERROR(IF(E24="","",E24-E23),"") | I24: =IF(H24="","",MAX(H24,0)) | J24: =IF(H24="","",MAX(-H24,0)) | K24: =IF(E24="","",IF(COUNT($E$4:E24)<5,"",AVERAGE(INDEX($E$4:E24,ROWS($E$4:E24)-4):E24))) | L24: =IF(E24="","",IF(COUNT($E$4:E24)<20,"",AVERAGE(INDEX($E$4:E24,ROWS($E$4:E24)-19):E24))) | M24: =IF(E24="","",IF(COUNT($E$4:E24)<60,"",AVERAGE(INDEX($E$4:E24,ROWS($E$4:E24)-59):E24))) | N24: =IF(E24="","",IF(COUNT($E$4:E24)<15,"",IF(SUM(INDEX($J$4:J24,ROWS($J$4:J24)-13):J24)=0,100,100-100/(1+SUM(INDEX($I$4:I24,ROWS($I$4:I24)-13):I24)/SUM(INDEX($J$4:J24,ROWS($J$4:J24)-13):J24))))) | O24: =IF(G24="","",IF(COUNT($G$4:G24)<20,"",_xlfn.STDEV.S(INDEX($G$4:G24,ROWS($G$4:G24)-19):G24)*SQRT($R$9)))
G25: =IFERROR(IF(E25="","",E25/E24-1),"") | H25: =IFERROR(IF(E25="","",E25-E24),"") | I25: =IF(H25="","",MAX(H25,0)) | J25: =IF(H25="","",MAX(-H25,0)) | K25: =IF(E25="","",IF(COUNT($E$4:E25)<5,"",AVERAGE(INDEX($E$4:E25,ROWS($E$4:E25)-4):E25))) | L25: =IF(E25="","",IF(COUNT($E$4:E25)<20,"",AVERAGE(INDEX($E$4:E25,ROWS($E$4:E25)-19):E25))) | M25: =IF(E25="","",IF(COUNT($E$4:E25)<60,"",AVERAGE(INDEX($E$4:E25,ROWS($E$4:E25)-59):E25))) | N25: =IF(E25="","",IF(COUNT($E$4:E25)<15,"",IF(SUM(INDEX($J$4:J25,ROWS($J$4:J25)-13):J25)=0,100,100-100/(1+SUM(INDEX($I$4:I25,ROWS($I$4:I25)-13):I25)/SUM(INDEX($J$4:J25,ROWS($J$4:J25)-13):J25))))) | O25: =IF(G25="","",IF(COUNT($G$4:G25)<20,"",_xlfn.STDEV.S(INDEX($G$4:G25,ROWS($G$4:G25)-19):G25)*SQRT($R$9)))
G26: =IFERROR(IF(E26="","",E26/E25-1),"") | H26: =IFERROR(IF(E26="","",E26-E25),"") | I26: =IF(H26="","",MAX(H26,0)) | J26: =IF(H26="","",MAX(-H26,0)) | K26: =IF(E26="","",IF(COUNT($E$4:E26)<5,"",AVERAGE(INDEX($E$4:E26,ROWS($E$4:E26)-4):E26))) | L26: =IF(E26="","",IF(COUNT($E$4:E26)<20,"",AVERAGE(INDEX($E$4:E26,ROWS($E$4:E26)-19):E26))) | M26: =IF(E26="","",IF(COUNT($E$4:E26)<60,"",AVERAGE(INDEX($E$4:E26,ROWS($E$4:E26)-59):E26))) | N26: =IF(E26="","",IF(COUNT($E$4:E26)<15,"",IF(SUM(INDEX($J$4:J26,ROWS($J$4:J26)-13):J26)=0,100,100-100/(1+SUM(INDEX($I$4:I26,ROWS($I$4:I26)-13):I26)/SUM(INDEX($J$4:J26,ROWS($J$4:J26)-13):J26))))) | O26: =IF(G26="","",IF(COUNT($G$4:G26)<20,"",_xlfn.STDEV.S(INDEX($G$4:G26,ROWS($G$4:G26)-19):G26)*SQRT($R$9)))
G27: =IFERROR(IF(E27="","",E27/E26-1),"") | H27: =IFERROR(IF(E27="","",E27-E26),"") | I27: =IF(H27="","",MAX(H27,0)) | J27: =IF(H27="","",MAX(-H27,0)) | K27: =IF(E27="","",IF(COUNT($E$4:E27)<5,"",AVERAGE(INDEX($E$4:E27,ROWS($E$4:E27)-4):E27))) | L27: =IF(E27="","",IF(COUNT($E$4:E27)<20,"",AVERAGE(INDEX($E$4:E27,ROWS($E$4:E27)-19):E27))) | M27: =IF(E27="","",IF(COUNT($E$4:E27)<60,"",AVERAGE(INDEX($E$4:E27,ROWS($E$4:E27)-59):E27))) | N27: =IF(E27="","",IF(COUNT($E$4:E27)<15,"",IF(SUM(INDEX($J$4:J27,ROWS($J$4:J27)-13):J27)=0,100,100-100/(1+SUM(INDEX($I$4:I27,ROWS($I$4:I27)-13):I27)/SUM(INDEX($J$4:J27,ROWS($J$4:J27)-13):J27))))) | O27: =IF(G27="","",IF(COUNT($G$4:G27)<20,"",_xlfn.STDEV.S(INDEX($G$4:G27,ROWS($G$4:G27)-19):G27)*SQRT($R$9)))
G28: =IFERROR(IF(E28="","",E28/E27-1),"") | H28: =IFERROR(IF(E28="","",E28-E27),"") | I28: =IF(H28="","",MAX(H28,0)) | J28: =IF(H28="","",MAX(-H28,0)) | K28: =IF(E28="","",IF(COUNT($E$4:E28)<5,"",AVERAGE(INDEX($E$4:E28,ROWS($E$4:E28)-4):E28))) | L28: =IF(E28="","",IF(COUNT($E$4:E28)<20,"",AVERAGE(INDEX($E$4:E28,ROWS($E$4:E28)-19):E28))) | M28: =IF(E28="","",IF(COUNT($E$4:E28)<60,"",AVERAGE(INDEX($E$4:E28,ROWS($E$4:E28)-59):E28))) | N28: =IF(E28="","",IF(COUNT($E$4:E28)<15,"",IF(SUM(INDEX($J$4:J28,ROWS($J$4:J28)-13):J28)=0,100,100-100/(1+SUM(INDEX($I$4:I28,ROWS($I$4:I28)-13):I28)/SUM(INDEX($J$4:J28,ROWS($J$4:J28)-13):J28))))) | O28: =IF(G28="","",IF(COUNT($G$4:G28)<20,"",_xlfn.STDEV.S(INDEX($G$4:G28,ROWS($G$4:G28)-19):G28)*SQRT($R$9)))
G29: =IFERROR(IF(E29="","",E29/E28-1),"") | H29: =IFERROR(IF(E29="","",E29-E28),"") | I29: =IF(H29="","",MAX(H29,0)) | J29: =IF(H29="","",MAX(-H29,0)) | K29: =IF(E29="","",IF(COUNT($E$4:E29)<5,"",AVERAGE(INDEX($E$4:E29,ROWS($E$4:E29)-4):E29))) | L29: =IF(E29="","",IF(COUNT($E$4:E29)<20,"",AVERAGE(INDEX($E$4:E29,ROWS($E$4:E29)-19):E29))) | M29: =IF(E29="","",IF(COUNT($E$4:E29)<60,"",AVERAGE(INDEX($E$4:E29,ROWS($E$4:E29)-59):E29))) | N29: =IF(E29="","",IF(COUNT($E$4:E29)<15,"",IF(SUM(INDEX($J$4:J29,ROWS($J$4:J29)-13):J29)=0,100,100-100/(1+SUM(INDEX($I$4:I29,ROWS($I$4:I29)-13):I29)/SUM(INDEX($J$4:J29,ROWS($J$4:J29)-13):J29))))) | O29: =IF(G29="","",IF(COUNT($G$4:G29)<20,"",_xlfn.STDEV.S(INDEX($G$4:G29,ROWS($G$4:G29)-19):G29)*SQRT($R$9)))
G30: =IFERROR(IF(E30="","",E30/E29-1),"") | H30: =IFERROR(IF(E30="","",E30-E29),"") | I30: =IF(H30="","",MAX(H30,0)) | J30: =IF(H30="","",MAX(-H30,0)) | K30: =IF(E30="","",IF(COUNT($E$4:E30)<5,"",AVERAGE(INDEX($E$4:E30,ROWS($E$4:E30)-4):E30))) | L30: =IF(E30="","",IF(COUNT($E$4:E30)<20,"",AVERAGE(INDEX($E$4:E30,ROWS($E$4:E30)-19):E30))) | M30: =IF(E30="","",IF(COUNT($E$4:E30)<60,"",AVERAGE(INDEX($E$4:E30,ROWS($E$4:E30)-59):E30))) | N30: =IF(E30="","",IF(COUNT($E$4:E30)<15,"",IF(SUM(INDEX($J$4:J30,ROWS($J$4:J30)-13):J30)=0,100,100-100/(1+SUM(INDEX($I$4:I30,ROWS($I$4:I30)-13):I30)/SUM(INDEX($J$4:J30,ROWS($J$4:J30)-13):J30))))) | O30: =IF(G30="","",IF(COUNT($G$4:G30)<20,"",_xlfn.STDEV.S(INDEX($G$4:G30,ROWS($G$4:G30)-19):G30)*SQRT($R$9)))
G31: =IFERROR(IF(E31="","",E31/E30-1),"") | H31: =IFERROR(IF(E31="","",E31-E30),"") | I31: =IF(H31="","",MAX(H31,0)) | J31: =IF(H31="","",MAX(-H31,0)) | K31: =IF(E31="","",IF(COUNT($E$4:E31)<5,"",AVERAGE(INDEX($E$4:E31,ROWS($E$4:E31)-4):E31))) | L31: =IF(E31="","",IF(COUNT($E$4:E31)<20,"",AVERAGE(INDEX($E$4:E31,ROWS($E$4:E31)-19):E31))) | M31: =IF(E31="","",IF(COUNT($E$4:E31)<60,"",AVERAGE(INDEX($E$4:E31,ROWS($E$4:E31)-59):E31))) | N31: =IF(E31="","",IF(COUNT($E$4:E31)<15,"",IF(SUM(INDEX($J$4:J31,ROWS($J$4:J31)-13):J31)=0,100,100-100/(1+SUM(INDEX($I$4:I31,ROWS($I$4:I31)-13):I31)/SUM(INDEX($J$4:J31,ROWS($J$4:J31)-13):J31))))) | O31: =IF(G31="","",IF(COUNT($G$4:G31)<20,"",_xlfn.STDEV.S(INDEX($G$4:G31,ROWS($G$4:G31)-19):G31)*SQRT($R$9)))
... G603: =IFERROR(IF(E603="","",E603/E602-1),"") | H603: =IFERROR(IF(E603="","",E603-E602),"") | I603: =IF(H603="","",MAX(H603,0)) | J603: =IF(H603="","",MAX(-H603,0)) | K603: =IF(E603="","",IF(COUNT($E$4:E603)<5,"",AVERAGE(INDEX($E$4:E603,ROWS($E$4:E603)-4):E603))) | L603: =IF(E603="","",IF(COUNT($E$4:E603)<20,"",AVERAGE(INDEX($E$4:E603,ROWS($E$4:E603)-19):E603))) | M603: =IF(E603="","",IF(COUNT($E$4:E603)<60,"",AVERAGE(INDEX($E$4:E603,ROWS($E$4:E603)-59):E603))) | N603: =IF(E603="","",IF(COUNT($E$4:E603)<15,"",IF(SUM(INDEX($J$4:J603,ROWS($J$4:J603)-13):J603)=0,100,100-100/(1+SUM(INDEX($I$4:I603,ROWS($I$4:I603)-13):I603)/SUM(INDEX($J$4:J603,ROWS($J$4:J603)-13):J603))))) | O603: =IF(G603="","",IF(COUNT($G$4:G603)<20,"",_xlfn.STDEV.S(INDEX($G$4:G603,ROWS($G$4:G603)-19):G603)*SQRT($R$9)))

Sheet 健檢快照
A1: 快照時間 | B1: 股票代號 | C1: 中文名稱 | D1: 英文名稱 | E1: 投資週期 | F1: 持有狀態 | G1: 持有成本（每股） | H1: 未實現損益（每股） | I1: 未實現損益率 | J1: 現價 | K1: 今日漲跌幅 | L1: 開盤價 | M1: 最高價 | N1: 最低價 | O1: 成交量 | P1: 量比 | Q1: 52 週價格位置 | R1: 5 日報酬 | S1: 20 日報酬 | T1: 60 日報酬 | U1: MA5 | V1: MA20 | W1: MA60 | X1: RSI（14） | Y1: 波動度（20 日年化） | Z1: 趨勢狀態 | AA1: 風險等級 | AB1: 52 週低點 | AC1: 52 週高點 | AD1: 市值 | AE1: 本益比 | AF1: EPS | AG1: Beta | AH1: 流通股數（手動） | AI1: 已發行股數 | AJ1: 幣別 | AK1: 最後交易時間 | AL1: 分析摘要－趨勢 | AM1: 分析摘要－量能 | AN1: 分析摘要－估值 | AO1: 分析摘要－風險 | AP1: 分析摘要－綜合 | AQ1: 觀察理由 | AR1: 催化因素 | AS1: 主要風險 | AT1: 下次檢查條件 | AU1: 個人結論
A2: 46234.418 | B2: TPE:2330 | C2: 台灣積體電路製造股份有限公司 | D2: Taiwan Semiconductor Manufacturng Co Ltd | E2: 波段（1–6 月） | F2: 觀察中 | J2: 2370 | K2: 0.0748 | L2: 2350 | M2: 2400 | N2: 2345 | O2: 21476796 | P2: 0.57x | Q2: 0.883 | R2: -0.0832 | S2: -0.1198 | T2: -0.02 | U2: 2277 | V2: 2383.5 | W2: 2345.17 | X2: 33.1 | Y2: 0.369 | Z2: 偏空震盪 | AA2: 中 | AB2: 1125 | AC2: 2535 | AD2: 61589378750000 | AE2: 27.2x | AF2: 87.38 | AI2: 25930379264 | AJ2: TWD | AK2: 46234.414 | AL2: 趨勢：偏空震盪；5／20／60 日報酬為 -8.3%／-12.0%／-2.0%。 | AM2: 今日成交量 21,476,796 股，量比 0.57x，量能偏弱。 | AN2: 市值 61,589,378,750,000 TWD；本益比 27.2x；EPS 87.38。 | AO2: 風險等級：中；RSI(14) 33.1；20 日年化波動度 36.9%；52 週位置 88.3%。 | AP2: 綜合判讀：訊號分歧，宜等待價格、量能與基本面出現一致性。 | AQ2: 現價 2,370.00 高於 MA5 2,277.00、低於 MA20 2,383.50、高於 MA60 2,345.17；5／20／60 日報酬 -8.3%／-12.0%／-2.0%，趨勢為 偏空震盪。RSI 33.1；量比 0.57x，量能偏弱。52 週位置 88.3%；本益比 27.2x，缺少歷史與同業比較，無法判斷估值高低。 | AR2: 可驗證的潛在催化：①收盤重新站上 MA5 2,277.00 或 MA20 2,383.50，並伴隨量比 ≥1.5x；②公司公布下一次月營收、季報／法說，以及資本支出或展望更新。試算表未提供公告日期、法人預期與新聞，基本面催化的時間及方向資料不足。 | AS2: 已反映：風險等級 中、20 日年化波動度 36.9%；現價相對 MA5／MA20／MA60 為 高於或等於／低於／高於或等於。待確認：客戶需求、先進製程產能／良率、匯率、出口管制與地緣事件；試算表無相關資料。RSI 33.1 僅為動能訊號，不代表已止跌。 | AT2: 每日收盤檢查：①站上 MA5 2,277.00 且量比 ≥1.5x，視為初步止跌；②站上 MA20 2,383.50（較佳為連續 2 日）再確認波段轉強；③收盤跌破今日低點 2,345.00 或 RSI 跌破 30 時提高警戒，RSI 回到 40 以上則觀察動能修復；④公司公布月營收、財報或法說後重評。 | AU2: 等待確認。投資週期為 波段（1–6 月）、持有狀態為 觀察中，持有成本未填（資料不足）；現價 2,370.00、RSI 33.1、量比 0.57x。建議先觀察價格與量能是否共同確認，結論為非絕對化追蹤判斷。
A3: 46234.438 | B3: TPE:2303 | C3: 聯華電子股份有限公司 | D3: United Microelectronics Corp | E3: 波段（1–6 月） | F3: 觀察中 | J3: 121 | K3: 0.1 | L3: 121 | M3: 121 | N3: 121 | O3: 36884207 | P3: 0.18x | Q3: 0.556 | R3: -0.2058 | S3: -0.3491 | T3: 0.3237 | U3: 116 | V3: 143.63 | W3: 135.52 | X3: 28.9 | Y3: 0.945 | Z3: 偏空震盪 | AA3: 高 | AB3: 40.1 | AC3: 185.5 | AD3: 1521814580000 | AE3: 30.4x | AF3: 3.98 | AI3: 12208239616 | AJ3: TWD | AK3: 46234.435 | AL3: 趨勢：偏空震盪；5／20／60 日報酬為 -20.6%／-34.9%／32.4%。 | AM3: 今日成交量 36,884,207 股，量比 0.18x，量能偏弱。 | AN3: 市值 1,521,814,580,000 TWD；本益比 30.4x；EPS 3.98。 | AO3: 風險等級：高；RSI(14) 28.9；20 日年化波動度 94.5%；52 週位置 55.6%。 | AP3: 綜合判讀：訊號分歧，宜等待價格、量能與基本面出現一致性。 | AQ3: 預設分析定義：請說明目前最值得追蹤的趨勢、量能、估值或價格位置。資料不足請註明，勿虛構。 | AR3: 預設分析定義：請列出可能改變股價或基本面的具體事件，不要只寫「市場轉好」等空泛內容。資料不足請註明，勿虛構。 | AS3: 預設分析定義：請指出目前數據已反映的風險，以及尚待確認的外部風險。資料不足請註明，勿虛構。 | AT3: 預設分析定義：請使用可以驗證的條件，例如突破或跌破 MA20／MA60、量比超過特定門檻、RSI 進入特定區間、接近 52 週高低點，或公司公布財報與法說。資料不足請註明，勿虛構。 | AU3: 預設分析定義：請根據投資週期、持有狀態與持有成本，給出「繼續觀察、等待確認、續抱追蹤、提高警戒」等明確但非絕對化的結論，並簡述原因。資料不足請註明，勿虛構。
A4: 46234.442 | B4: TPE:2303 | C4: 聯華電子股份有限公司 | D4: United Microelectronics Corp | E4: 波段（1–6 月） | F4: 觀察中 | G4: 144 | H4: -23 | I4: -0.1597 | J4: 121 | K4: 0.1 | L4: 121 | M4: 121 | N4: 121 | O4: 36884207 | P4: 0.18x | Q4: 0.556 | R4: -0.2058 | S4: -0.3491 | T4: 0.3237 | U4: 116 | V4: 143.63 | W4: 135.52 | X4: 28.9 | Y4: 0.945 | Z4: 偏空震盪 | AA4: 高 | AB4: 40.1 | AC4: 185.5 | AD4: 1521814580000 | AE4: 30.4x | AF4: 3.98 | AI4: 12208239616 | AJ4: TWD | AK4: 46234.435 | AL4: 趨勢：偏空震盪；5／20／60 日報酬為 -20.6%／-34.9%／32.4%。 | AM4: 今日成交量 36,884,207 股，量比 0.18x，量能偏弱。 | AN4: 市值 1,521,814,580,000 TWD；本益比 30.4x；EPS 3.98。 | AO4: 風險等級：高；RSI(14) 28.9；20 日年化波動度 94.5%；52 週位置 55.6%。 | AP4: 綜合判讀：訊號分歧，宜等待價格、量能與基本面出現一致性。 | AQ4: 預設分析定義：請說明目前最值得追蹤的趨勢、量能、估值或價格位置。資料不足請註明，勿虛構。 | AR4: 預設分析定義：請列出可能改變股價或基本面的具體事件，不要只寫「市場轉好」等空泛內容。資料不足請註明，勿虛構。 | AS4: 預設分析定義：請指出目前數據已反映的風險，以及尚待確認的外部風險。資料不足請註明，勿虛構。 | AT4: 預設分析定義：請使用可以驗證的條件，例如突破或跌破 MA20／MA60、量比超過特定門檻、RSI 進入特定區間、接近 52 週高低點，或公司公布財報與法說。資料不足請註明，勿虛構。 | AU4: 預設分析定義：請根據投資週期、持有狀態與持有成本，給出「繼續觀察、等待確認、續抱追蹤、提高警戒」等明確但非絕對化的結論，並簡述原因。資料不足請註明，勿虛構。
A5: 46234.443 | B5: TPE:2303 | C5: 聯華電子股份有限公司 | D5: United Microelectronics Corp | E5: 波段（1–6 月） | F5: 持有中 | G5: 144 | H5: -23 | I5: -0.1597 | J5: 121 | K5: 0.1 | L5: 121 | M5: 121 | N5: 121 | O5: 36884207 | P5: 0.18x | Q5: 0.556 | R5: -0.2058 | S5: -0.3491 | T5: 0.3237 | U5: 116 | V5: 143.63 | W5: 135.52 | X5: 28.9 | Y5: 0.945 | Z5: 偏空震盪 | AA5: 高 | AB5: 40.1 | AC5: 185.5 | AD5: 1521814580000 | AE5: 30.4x | AF5: 3.98 | AI5: 12208239616 | AJ5: TWD | AK5: 46234.435 | AL5: 趨勢：偏空震盪；5／20／60 日報酬為 -20.6%／-34.9%／32.4%。 | AM5: 今日成交量 36,884,207 股，量比 0.18x，量能偏弱。 | AN5: 市值 1,521,814,580,000 TWD；本益比 30.4x；EPS 3.98。 | AO5: 風險等級：高；RSI(14) 28.9；20 日年化波動度 94.5%；52 週位置 55.6%。 | AP5: 綜合判讀：訊號分歧，宜等待價格、量能與基本面出現一致性。 | AQ5: 預設分析定義：請說明目前最值得追蹤的趨勢、量能、估值或價格位置。資料不足請註明，勿虛構。 | AR5: 預設分析定義：請列出可能改變股價或基本面的具體事件，不要只寫「市場轉好」等空泛內容。資料不足請註明，勿虛構。 | AS5: 預設分析定義：請指出目前數據已反映的風險，以及尚待確認的外部風險。資料不足請註明，勿虛構。 | AT5: 預設分析定義：請使用可以驗證的條件，例如突破或跌破 MA20／MA60、量比超過特定門檻、RSI 進入特定區間、接近 52 週高低點，或公司公布財報與法說。資料不足請註明，勿虛構。 | AU5: 預設分析定義：請根據投資週期、持有狀態與持有成本，給出「繼續觀察、等待確認、續抱追蹤、提高警戒」等明確但非絕對化的結論，並簡述原因。資料不足請註明，勿虛構。
